edx_toggles/__init__.py
edx_toggles/apps.py
edx_toggles/models.py
edx_toggles/urls.py
edx_toggles/tests/__init__.py
edx_toggles/tests/test_setting_toggles.py
edx_toggles/tests/test_state.py
edx_toggles/tests/test_testutils.py
edx_toggles/tests/test_waffle.py
edx_toggles/toggles/__init__.py
edx_toggles/toggles/testutils.py
edx_toggles/toggles/internal/__init__.py
edx_toggles/toggles/internal/base.py
edx_toggles/toggles/internal/setting_toggle.py
edx_toggles/toggles/internal/waffle/__init__.py
edx_toggles/toggles/internal/waffle/base.py
edx_toggles/toggles/internal/waffle/cache.py
edx_toggles/toggles/internal/waffle/flag.py
edx_toggles/toggles/internal/waffle/switch.py
edx_toggles/toggles/state/__init__.py
edx_toggles/toggles/state/internal/__init__.py
edx_toggles/toggles/state/internal/report.py
edx_toggles-5.4.1.dist-info/licenses/LICENSE.txt
edx_toggles-5.4.1.dist-info/METADATA
edx_toggles-5.4.1.dist-info/WHEEL
edx_toggles-5.4.1.dist-info/entry_points.txt
edx_toggles-5.4.1.dist-info/top_level.txt
edx_toggles-5.4.1.dist-info/RECORD
