Metadata-Version: 2.4
Name: edx-toggles
Version: 5.4.1
Summary: Library and utilities for feature toggles
Home-page: https://github.com/openedx/edx-toggles
Author: edX
Author-email: oscm@edx.org
License: AGPL 3.0
Keywords: Django edx
Classifier: Development Status :: 3 - Alpha
Classifier: Framework :: Django
Classifier: Framework :: Django :: 4.2
Classifier: Framework :: Django :: 5.2
Classifier: Intended Audience :: Developers
Classifier: License :: OSI Approved :: GNU Affero General Public License v3 or later (AGPLv3+)
Classifier: Natural Language :: English
Classifier: Programming Language :: Python :: 3
Classifier: Programming Language :: Python :: 3.11
Classifier: Programming Language :: Python :: 3.12
License-File: LICENSE.txt
Requires-Dist: Django>=2.2
Requires-Dist: code-annotations
Requires-Dist: django-crum
Requires-Dist: django-waffle
Requires-Dist: edx-django-utils
Dynamic: author
Dynamic: author-email
Dynamic: classifier
Dynamic: description
Dynamic: home-page
Dynamic: keywords
Dynamic: license
Dynamic: license-file
Dynamic: requires-dist
Dynamic: summary
